kinto_hawk/__init__.py
kinto_hawk/authentication.py
kinto_hawk/tweens.py
kinto_hawk/views.py
kinto_hawk-0.1.0.dist-info/DESCRIPTION.rst
kinto_hawk-0.1.0.dist-info/METADATA
kinto_hawk-0.1.0.dist-info/RECORD
kinto_hawk-0.1.0.dist-info/WHEEL
kinto_hawk-0.1.0.dist-info/metadata.json
kinto_hawk-0.1.0.dist-info/top_level.txt
tests/__init__.py
tests/test_authentication.py
tests/test_includeme.py
