Metadata-Version: 2.0
Name: kinto-hawk
Version: 0.1.0
Summary: Hawk authentication support for Kinto
Home-page: https://github.com/Kinto/kinto-hawk
Author: Rémy Hubscher
Author-email: hubscher.remy@gmail.com
License: Apache License (2.0)
Keywords: web services
Platform: UNKNOWN
Classifier: Programming Language :: Python
Classifier: Programming Language :: Python :: 3
Classifier: Programming Language :: Python :: 3.5
Classifier: Programming Language :: Python :: 3.6
Classifier: Topic :: Internet :: WWW/HTTP
Classifier: Topic :: Internet :: WWW/HTTP :: WSGI :: Application
Classifier: License :: OSI Approved :: Apache Software License
Requires-Dist: kinto (>=7)
Requires-Dist: requests-hawk
